adafruit_circuitpython_matrixportal-3.2.9.dist-info/licenses/LICENSE
adafruit_matrixportal/__init__.py
adafruit_matrixportal/graphics.py
adafruit_matrixportal/matrix.py
adafruit_matrixportal/matrixportal.py
adafruit_matrixportal/network.py
adafruit_circuitpython_matrixportal-3.2.9.dist-info/METADATA
adafruit_circuitpython_matrixportal-3.2.9.dist-info/WHEEL
adafruit_circuitpython_matrixportal-3.2.9.dist-info/top_level.txt
adafruit_circuitpython_matrixportal-3.2.9.dist-info/RECORD
