Metadata-Version: 2.4
Name: adafruit-circuitpython-matrixportal
Version: 3.2.9
Summary: CircuitPython helper for Adafruit MatrixPortal M4, Adafruit RGB Matrix Shield + Metro M4 Airlift Lite, and Adafruit RGB Matrix FeatherWings
Author-email: Adafruit Industries <circuitpython@adafruit.com>
License: MIT
Project-URL: Homepage, https://github.com/adafruit/Adafruit_CircuitPython_MatrixPortal
Keywords: adafruit,matrixportal,matrix,rgb,led,feather,featherwing,shieldbreakout,hardware,micropython,circuitpython
Classifier: Intended Audience :: Developers
Classifier: Topic :: Software Development :: Libraries
Classifier: Topic :: Software Development :: Embedded Systems
Classifier: Topic :: System :: Hardware
Classifier: License :: OSI Approved :: MIT License
Classifier: Programming Language :: Python :: 3
License-File: LICENSE
Requires-Dist: Adafruit-Blinka-displayio
Requires-Dist: Adafruit-Blinka
Requires-Dist: adafruit-circuitpython-bitmap-font
Requires-Dist: adafruit-circuitpython-display-text
Requires-Dist: adafruit-circuitpython-esp32spi
Requires-Dist: adafruit-circuitpython-adafruitio
Requires-Dist: adafruit-circuitpython-requests
Requires-Dist: adafruit-circuitpython-neopixel
Requires-Dist: adafruit-circuitpython-portalbase
Provides-Extra: optional
Dynamic: license-file
